{"assets":{"543365F5B4A3C4D137C2D64741ED3808":{"type":"texture","index":6,"assetRequest":{"type":"slide","state":"contents","slide":"none"},"url":{"native":"assets\/C38089FB-CBF3-471E-B091-34E4297FA557.pdf"},"width":1286,"height":297},"C25C25FF361FB24FC35F6B120D2F252D":{"type":"texture","index":0,"assetRequest":{"type":"slide","state":"contents","slide":"none"},"url":{"native":"assets\/C38089FB-CBF3-471E-B091-34E4297FA557.pdf"},"width":1920,"height":1080},"8A911023D4EDFC96539956C0779A9E6F":{"type":"texture","index":3,"assetRequest":{"type":"slide","state":"contents","slide":"none"},"url":{"native":"assets\/C38089FB-CBF3-471E-B091-34E4297FA557.pdf"},"width":1286,"height":297},"DCE86DF318B804319ABC889B8087A5D0":{"type":"texture","index":1,"assetRequest":{"type":"slide","state":"contents","slide":"none"},"url":{"native":"assets\/C38089FB-CBF3-471E-B091-34E4297FA557.pdf"},"width":1370,"height":1449},"86B773CE04C51B52335229BE21F057BB":{"type":"texture","index":2,"assetRequest":{"type":"slide","state":"contents","slide":"none"},"url":{"native":"assets\/C38089FB-CBF3-471E-B091-34E4297FA557.pdf"},"width":1287,"height":296},"295871E4FE9EF3209C04A2B748B0E435":{"type":"texture","index":5,"assetRequest":{"type":"slide","state":"contents","slide":"none"},"url":{"native":"assets\/C38089FB-CBF3-471E-B091-34E4297FA557.pdf"},"width":1371,"height":1450},"5C22B10F9DC8C973BFF8E2CEBB5FD141":{"type":"texture","index":4,"assetRequest":{"type":"slide","state":"contents","slide":"none"},"url":{"native":"assets\/C38089FB-CBF3-471E-B091-34E4297FA557.pdf"},"width":1044,"height":79}},"events":[{"effects":[{"beginTime":0,"baseLayer":{"animations":[],"initialState":{"affineTransform":[1,0,0,1,0,0],"masksToBounds":false,"rotation":0,"scale":1,"position":{"pointX":960,"pointY":540},"width":1920,"sublayerTransform":[1,0,0,0,0,1,0,0,0,0,1,0,0,0,0,1],"contentsRect":{"y":0,"x":0,"width":1,"height":1},"opacity":1,"edgeAntialiasingMask":251658240,"height":1080,"hidden":false,"anchorPoint":{"pointX":0.5,"pointY":0.5}},"objectID":"0","layers":[{"animations":[],"initialState":{"affineTransform":[1,0,0,1,0,0],"masksToBounds":false,"rotation":0,"scale":1,"position":{"pointX":960,"pointY":540},"width":1920,"sublayerTransform":[1,0,0,0,0,1,0,0,0,0,1,-0.00035007912466775983,0,0,0,1],"contentsRect":{"y":0,"x":0,"width":1,"height":1},"opacity":1,"edgeAntialiasingMask":251658240,"height":1080,"hidden":false,"anchorPoint":{"pointX":0.5,"pointY":0.5}},"layers":[{"animations":[{"additive":false,"timeOffset":0,"beginTime":0,"repeatCount":0,"fillMode":"both","duration":2,"autoreverses":false,"animations":[{"repeatCount":0,"removedOnCompletion":true,"from":{"scalar":0},"timingFunction":"EaseInEaseOut","additive":false,"timeOffset":0,"autoreverses":false,"property":"zPosition","fillMode":"both","duration":2,"beginTime":0,"to":{"scalar":0}}],"removedOnCompletion":false}],"initialState":{"affineTransform":[1,0,0,1,0,0],"masksToBounds":false,"rotation":0,"scale":1,"position":{"pointX":960,"pointY":540},"width":1920,"sublayerTransform":[1,0,0,0,0,1,0,0,0,0,1,0,0,0,0,1],"contentsRect":{"y":0,"x":0,"width":1,"height":1},"opacity":1,"edgeAntialiasingMask":251658240,"height":1080,"hidden":false,"anchorPoint":{"pointX":0.5,"pointY":0.5}},"layers":[{"animations":[],"layers":[],"texturedRectangle":{"isBackgroundTexture":true,"singleTextureOpacity":1,"textureType":1,"textBaseline":0,"textXHeight":0,"isVerticalText":false},"initialState":{"affineTransform":[1,0,0,1,0,0],"masksToBounds":false,"rotation":0,"scale":1,"position":{"pointX":960,"pointY":540},"width":1920,"sublayerTransform":[1,0,0,0,0,1,0,0,0,0,1,0,0,0,0,1],"contentsRect":{"y":0,"x":0,"width":1,"height":1},"opacity":1,"edgeAntialiasingMask":0,"height":1080,"hidden":false,"anchorPoint":{"pointX":0.5,"pointY":0.5}},"texture":"C25C25FF361FB24FC35F6B120D2F252D"}]}]},{"animations":[{"additive":false,"timeOffset":0,"beginTime":0,"repeatCount":0,"fillMode":"both","duration":2,"autoreverses":false,"animations":[{"repeatCount":0,"removedOnCompletion":true,"from":{"scalar":0.001},"timingFunction":"EaseInEaseOut","additive":false,"timeOffset":0,"autoreverses":false,"property":"zPosition","fillMode":"both","duration":2,"beginTime":0,"to":{"scalar":0.001}}],"removedOnCompletion":false}],"initialState":{"affineTransform":[1,0,0,1,0,0],"masksToBounds":false,"rotation":0,"scale":1,"position":{"pointX":1287.1311645507812,"pointY":995.51160907745361},"width":1367.5625,"sublayerTransform":[1,0,0,0,0,1,0,0,0,0,1,0,0,0,0,1],"contentsRect":{"y":0,"x":0,"width":1,"height":1},"opacity":1,"edgeAntialiasingMask":251658240,"height":1446.8239688873291,"hidden":false,"anchorPoint":{"pointX":0.5,"pointY":0.5}},"layers":[{"animations":[{"additive":false,"timeOffset":0,"beginTime":0,"repeatCount":0,"fillMode":"both","duration":2,"autoreverses":false,"animations":[{"repeatCount":0,"removedOnCompletion":true,"from":{"scalar":1},"timingFunction":"EaseInEaseOut","additive":false,"timeOffset":0,"autoreverses":false,"property":"transform.scale.x","fillMode":"both","duration":2,"beginTime":0,"to":{"scalar":1.0007299270072993}},{"repeatCount":0,"removedOnCompletion":true,"from":{"scalar":1},"timingFunction":"EaseInEaseOut","additive":false,"timeOffset":0,"autoreverses":false,"property":"transform.scale.y","fillMode":"both","duration":2,"beginTime":0,"to":{"scalar":1.0006901311249137}},{"repeatCount":0,"removedOnCompletion":true,"from":{"texture":"DCE86DF318B804319ABC889B8087A5D0"},"timingFunction":"EaseInEaseOut","additive":false,"timeOffset":0,"autoreverses":false,"property":"contents","fillMode":"both","duration":1.3333999999999999,"beginTime":0,"to":{"texture":"295871E4FE9EF3209C04A2B748B0E435"}},{"repeatCount":0,"removedOnCompletion":true,"from":{"pointX":0,"pointY":0},"timingFunction":"EaseInEaseOut","additive":false,"timeOffset":0,"autoreverses":false,"property":"transform.translation","fillMode":"both","duration":2,"beginTime":0,"to":{"pointX":16.500092628549737,"pointY":-482.49999198821422}}],"removedOnCompletion":false}],"layers":[],"texturedRectangle":{"isBackgroundTexture":true,"singleTextureOpacity":1,"textureType":5,"textBaseline":0,"textXHeight":0,"isVerticalText":false},"initialState":{"affineTransform":[1,0,0,1,0,0],"masksToBounds":false,"rotation":0,"scale":1,"position":{"pointX":683.77698656242501,"pointY":723.41198444366455},"width":1370,"sublayerTransform":[1,0,0,0,0,1,0,0,0,0,1,0,0,0,0,1],"contentsRect":{"y":0,"x":0,"width":1,"height":1},"opacity":1,"edgeAntialiasingMask":0,"height":1449,"hidden":false,"anchorPoint":{"pointX":0.50009262854978564,"pointY":0.50000801178568233}},"texture":"DCE86DF318B804319ABC889B8087A5D0"}]},{"animations":[{"additive":false,"timeOffset":0,"beginTime":0,"repeatCount":0,"fillMode":"both","duration":2,"autoreverses":false,"animations":[{"repeatCount":0,"removedOnCompletion":true,"from":{"scalar":0.002},"timingFunction":"EaseInEaseOut","additive":false,"timeOffset":0,"autoreverses":false,"property":"zPosition","fillMode":"both","duration":2,"beginTime":0,"to":{"scalar":0.002}}],"removedOnCompletion":false}],"initialState":{"affineTransform":[1,0,0,1,0,0],"masksToBounds":false,"rotation":0,"scale":1,"position":{"pointX":1261.5581054687491,"pointY":933.2306213378904},"width":1283.3150634765639,"sublayerTransform":[1,0,0,0,0,1,0,0,0,0,1,0,0,0,0,1],"contentsRect":{"y":0,"x":0,"width":1,"height":1},"opacity":1,"edgeAntialiasingMask":251658240,"height":293.53875732421909,"hidden":false,"anchorPoint":{"pointX":0.5,"pointY":0.5}},"layers":[{"animations":[{"additive":false,"timeOffset":0,"beginTime":0,"repeatCount":0,"fillMode":"both","duration":2,"autoreverses":false,"animations":[{"repeatCount":0,"removedOnCompletion":true,"from":{"texture":"86B773CE04C51B52335229BE21F057BB"},"timingFunction":"EaseInEaseOut","additive":false,"timeOffset":0,"autoreverses":false,"property":"contents","fillMode":"both","duration":2,"beginTime":0,"to":{"texture":"86B773CE04C51B52335229BE21F057BB"}}],"removedOnCompletion":false}],"layers":[],"texturedRectangle":{"singleTextureOpacity":1,"textXHeight":0,"shapePath":{"lineWidth":1,"flatness":0.59999999999999998,"lineCapStyle":0,"elements":[{"type":"MoveToPoint","points":[[1.9005737304672721,1.4612426757809089]]},{"type":"AddLine","points":[[1285.2156372070312,1.4612426757809089]]},{"type":"AddLine","points":[[1285.2156372070312,295]]},{"type":"AddLine","points":[[1.9005737304672721,295]]},{"type":"CloseSubpath"},{"type":"MoveToPoint","points":[[1.9005737304672721,1.4612426757809089]]}],"windingRule":0,"lineJoinStyle":0,"miterLimit":10},"isBackgroundTexture":true,"textBaseline":0,"isVerticalText":false,"textureType":5},"initialState":{"affineTransform":[1,0,0,1,0,0],"masksToBounds":false,"rotation":0,"scale":1,"position":{"pointX":641.65753173828273,"pointY":146.76937866210972},"width":1287,"sublayerTransform":[1,0,0,0,0,1,0,0,0,0,1,0,0,0,0,1],"contentsRect":{"y":0,"x":0,"width":1,"height":1},"opacity":1,"edgeAntialiasingMask":0,"height":296,"hidden":false,"anchorPoint":{"pointX":0.50004514799436672,"pointY":0.50077912614152242}},"texture":"86B773CE04C51B52335229BE21F057BB"}]},{"animations":[{"additive":false,"timeOffset":0,"beginTime":0,"repeatCount":0,"fillMode":"both","duration":2,"autoreverses":false,"animations":[{"repeatCount":0,"removedOnCompletion":true,"from":{"scalar":0.0030000000000000001},"timingFunction":"EaseInEaseOut","additive":false,"timeOffset":0,"autoreverses":false,"property":"zPosition","fillMode":"both","duration":2,"beginTime":0,"to":{"scalar":0.0030000000000000001}}],"removedOnCompletion":false}],"initialState":{"affineTransform":[1,0,0,1,0,0],"masksToBounds":false,"rotation":0,"scale":1,"position":{"pointX":1329.2548828124991,"pointY":147.66420596837986},"width":1283.3150634765639,"sublayerTransform":[1,0,0,0,0,1,0,0,0,0,1,0,0,0,0,1],"contentsRect":{"y":0,"x":0,"width":1,"height":1},"opacity":1,"edgeAntialiasingMask":251658240,"height":293.53875732421909,"hidden":false,"anchorPoint":{"pointX":0.5,"pointY":0.5}},"layers":[{"animations":[{"additive":false,"timeOffset":0,"beginTime":0,"repeatCount":0,"fillMode":"both","duration":2,"autoreverses":false,"animations":[{"repeatCount":0,"removedOnCompletion":true,"from":{"texture":"8A911023D4EDFC96539956C0779A9E6F"},"timingFunction":"EaseInEaseOut","additive":false,"timeOffset":0,"autoreverses":false,"property":"contents","fillMode":"both","duration":2,"beginTime":0,"to":{"texture":"543365F5B4A3C4D137C2D64741ED3808"}},{"additive":false,"timeOffset":0,"beginTime":0,"from":{"scalar":-3.1415926535897931},"repeatCount":0,"fillMode":"both","duration":2,"autoreverses":false,"property":"transform.rotation.z","to":{"scalar":-3.1415926535897931},"removedOnCompletion":true}],"removedOnCompletion":false}],"layers":[],"texturedRectangle":{"singleTextureOpacity":1,"textXHeight":0,"shapePath":{"lineWidth":1,"flatness":0.59999999999999998,"lineCapStyle":0,"elements":[{"type":"MoveToPoint","points":[[1284.9124145507826,295.4335846304898]]},{"type":"AddLine","points":[[1.59735107421875,295.43358463048963]]},{"type":"AddLine","points":[[1.59735107421875,1.8948273062705425]]},{"type":"AddLine","points":[[1284.9124145507826,1.8948273062707131]]},{"type":"CloseSubpath"},{"type":"MoveToPoint","points":[[1284.9124145507826,295.4335846304898]]}],"windingRule":0,"lineJoinStyle":0,"miterLimit":10},"isBackgroundTexture":true,"textBaseline":0,"isVerticalText":false,"textureType":5},"initialState":{"affineTransform":[-1,0,0,-1,0,0],"masksToBounds":false,"rotation":3.1415926535897931,"scale":1,"position":{"pointX":641.65753173828284,"pointY":146.76937866210966},"width":1286,"sublayerTransform":[1,0,0,0,0,1,0,0,0,0,1,0,0,0,0,1],"contentsRect":{"y":0,"x":0,"width":1,"height":1},"opacity":1,"edgeAntialiasingMask":0,"height":297,"hidden":false,"anchorPoint":{"pointX":0.50019819814346811,"pointY":0.50055288204841752}},"texture":"8A911023D4EDFC96539956C0779A9E6F"}]},{"animations":[{"additive":false,"timeOffset":0,"beginTime":0,"repeatCount":0,"fillMode":"both","duration":2,"autoreverses":false,"animations":[{"repeatCount":0,"removedOnCompletion":true,"from":{"scalar":0.0040000000000000001},"timingFunction":"EaseInEaseOut","additive":false,"timeOffset":0,"autoreverses":false,"property":"zPosition","fillMode":"both","duration":2,"beginTime":0,"to":{"scalar":0.0040000000000000001}}],"removedOnCompletion":false}],"initialState":{"affineTransform":[1,0,0,1,0,0],"masksToBounds":false,"rotation":0,"scale":1,"position":{"pointX":564.6436882019043,"pointY":97.284202575683594},"width":1049.3200302124023,"sublayerTransform":[1,0,0,0,0,1,0,0,0,0,1,0,0,0,0,1],"contentsRect":{"y":0,"x":0,"width":1,"height":1},"opacity":1,"edgeAntialiasingMask":251658240,"height":100.76000690460205,"hidden":false,"anchorPoint":{"pointX":0.5,"pointY":0.5}},"layers":[{"animations":[{"additive":false,"timeOffset":0,"beginTime":0,"repeatCount":0,"fillMode":"both","duration":2,"autoreverses":false,"animations":[{"repeatCount":0,"removedOnCompletion":true,"from":{"texture":"5C22B10F9DC8C973BFF8E2CEBB5FD141"},"timingFunction":"EaseInEaseOut","additive":false,"timeOffset":0,"autoreverses":false,"property":"contents","fillMode":"both","duration":2,"beginTime":0,"to":{"texture":"5C22B10F9DC8C973BFF8E2CEBB5FD141"}}],"removedOnCompletion":false}],"layers":[],"texturedRectangle":{"singleTextureOpacity":1,"textXHeight":0.5235443037974683,"textBaseline":0.76739764515357678,"isBackgroundTexture":true,"isVerticalText":false,"textColor":[0,0,0,1],"textureType":6},"initialState":{"affineTransform":[1,0,0,1,0,0],"masksToBounds":false,"rotation":0,"scale":1,"position":{"pointX":524.66000000000008,"pointY":50.3800048828125},"width":1044,"sublayerTransform":[1,0,0,0,0,1,0,0,0,0,1,0,0,0,0,1],"contentsRect":{"y":0,"x":0,"width":1,"height":1},"opacity":1,"edgeAntialiasingMask":0,"height":79,"hidden":false,"anchorPoint":{"pointX":0.50157439951695715,"pointY":0.39600258235689961}},"texture":"5C22B10F9DC8C973BFF8E2CEBB5FD141"}]}]},"effects":[],"duration":2,"type":"transition","attributes":{"direction":0},"name":"apple:magic-move-implied-motion-path","objectID":"0"}],"automaticPlay":false,"hyperlinks":[],"accessibility":[{"text":"how_acs_works.png","targetRectangle":{"y":272.09962463378906,"x":603.34991455078125,"width":1367.5625,"height":1446.8239688873291}},{"text":"American Community Survey","targetRectangle":{"y":50.904199123382568,"x":43.983673095703125,"width":1040.3200000000002,"height":92.760009765625}}],"baseLayer":{"animations":[],"initialState":{"affineTransform":[1,0,0,1,0,0],"masksToBounds":false,"rotation":0,"scale":1,"position":{"pointX":960,"pointY":540},"width":1920,"sublayerTransform":[1,0,0,0,0,1,0,0,0,0,1,0,0,0,0,1],"contentsRect":{"y":0,"x":0,"width":1,"height":1},"opacity":1,"edgeAntialiasingMask":251658240,"height":1080,"hidden":false,"anchorPoint":{"pointX":0.5,"pointY":0.5}},"objectID":"0","layers":[{"animations":[],"initialState":{"affineTransform":[1,0,0,1,0,0],"masksToBounds":false,"rotation":0,"scale":1,"position":{"pointX":960,"pointY":540},"width":1920,"sublayerTransform":[1,0,0,0,0,1,0,0,0,0,1,-0.00035007912466775983,0,0,0,1],"contentsRect":{"y":0,"x":0,"width":1,"height":1},"opacity":1,"edgeAntialiasingMask":251658240,"height":1080,"hidden":false,"anchorPoint":{"pointX":0.5,"pointY":0.5}},"layers":[{"animations":[],"initialState":{"affineTransform":[1,0,0,1,0,0],"masksToBounds":false,"rotation":0,"scale":1,"position":{"pointX":960,"pointY":540},"width":1920,"sublayerTransform":[1,0,0,0,0,1,0,0,0,0,1,0,0,0,0,1],"contentsRect":{"y":0,"x":0,"width":1,"height":1},"opacity":1,"edgeAntialiasingMask":251658240,"height":1080,"hidden":false,"anchorPoint":{"pointX":0.5,"pointY":0.5}},"layers":[{"animations":[],"layers":[],"texturedRectangle":{"isBackgroundTexture":true,"singleTextureOpacity":1,"textureType":1,"textBaseline":0,"textXHeight":0,"isVerticalText":false},"initialState":{"affineTransform":[1,0,0,1,0,0],"masksToBounds":false,"rotation":0,"scale":1,"position":{"pointX":960,"pointY":540},"width":1920,"sublayerTransform":[1,0,0,0,0,1,0,0,0,0,1,0,0,0,0,1],"contentsRect":{"y":0,"x":0,"width":1,"height":1},"opacity":1,"edgeAntialiasingMask":0,"height":1080,"hidden":false,"anchorPoint":{"pointX":0.5,"pointY":0.5}},"texture":"C25C25FF361FB24FC35F6B120D2F252D"}]}]},{"animations":[],"initialState":{"affineTransform":[1,0,0,1,0,0],"masksToBounds":false,"rotation":0,"scale":1,"position":{"pointX":1287.1311645507812,"pointY":995.51160907745361},"width":1367.5625,"sublayerTransform":[1,0,0,0,0,1,0,0,0,0,1,0,0,0,0,1],"contentsRect":{"y":0,"x":0,"width":1,"height":1},"opacity":1,"edgeAntialiasingMask":251658240,"height":1446.8239688873291,"hidden":false,"anchorPoint":{"pointX":0.5,"pointY":0.5}},"layers":[{"animations":[],"layers":[],"texturedRectangle":{"isBackgroundTexture":true,"singleTextureOpacity":1,"textureType":5,"textBaseline":0,"textXHeight":0,"isVerticalText":false},"initialState":{"affineTransform":[1,0,0,1,0,0],"masksToBounds":false,"rotation":0,"scale":1,"position":{"pointX":683.77698656242501,"pointY":723.41198444366455},"width":1370,"sublayerTransform":[1,0,0,0,0,1,0,0,0,0,1,0,0,0,0,1],"contentsRect":{"y":0,"x":0,"width":1,"height":1},"opacity":1,"edgeAntialiasingMask":0,"height":1449,"hidden":false,"anchorPoint":{"pointX":0.50009262854978564,"pointY":0.50000801178568233}},"texture":"DCE86DF318B804319ABC889B8087A5D0"}]},{"animations":[],"initialState":{"affineTransform":[1,0,0,1,0,0],"masksToBounds":false,"rotation":0,"scale":1,"position":{"pointX":1261.5581054687491,"pointY":933.2306213378904},"width":1283.3150634765639,"sublayerTransform":[1,0,0,0,0,1,0,0,0,0,1,0,0,0,0,1],"contentsRect":{"y":0,"x":0,"width":1,"height":1},"opacity":1,"edgeAntialiasingMask":251658240,"height":293.53875732421909,"hidden":false,"anchorPoint":{"pointX":0.5,"pointY":0.5}},"layers":[{"animations":[],"layers":[],"texturedRectangle":{"singleTextureOpacity":1,"textXHeight":0,"shapePath":{"lineWidth":1,"flatness":0.59999999999999998,"lineCapStyle":0,"elements":[{"type":"MoveToPoint","points":[[1.9005737304672721,1.4612426757809089]]},{"type":"AddLine","points":[[1285.2156372070312,1.4612426757809089]]},{"type":"AddLine","points":[[1285.2156372070312,295]]},{"type":"AddLine","points":[[1.9005737304672721,295]]},{"type":"CloseSubpath"},{"type":"MoveToPoint","points":[[1.9005737304672721,1.4612426757809089]]}],"windingRule":0,"lineJoinStyle":0,"miterLimit":10},"isBackgroundTexture":true,"textBaseline":0,"isVerticalText":false,"textureType":5},"initialState":{"affineTransform":[1,0,0,1,0,0],"masksToBounds":false,"rotation":0,"scale":1,"position":{"pointX":641.65753173828273,"pointY":146.76937866210972},"width":1287,"sublayerTransform":[1,0,0,0,0,1,0,0,0,0,1,0,0,0,0,1],"contentsRect":{"y":0,"x":0,"width":1,"height":1},"opacity":1,"edgeAntialiasingMask":0,"height":296,"hidden":false,"anchorPoint":{"pointX":0.50004514799436672,"pointY":0.50077912614152242}},"texture":"86B773CE04C51B52335229BE21F057BB"}]},{"animations":[],"initialState":{"affineTransform":[1,0,0,1,0,0],"masksToBounds":false,"rotation":0,"scale":1,"position":{"pointX":1329.2548828124991,"pointY":147.66420596837986},"width":1283.3150634765639,"sublayerTransform":[1,0,0,0,0,1,0,0,0,0,1,0,0,0,0,1],"contentsRect":{"y":0,"x":0,"width":1,"height":1},"opacity":1,"edgeAntialiasingMask":251658240,"height":293.53875732421909,"hidden":false,"anchorPoint":{"pointX":0.5,"pointY":0.5}},"layers":[{"animations":[],"layers":[],"texturedRectangle":{"singleTextureOpacity":1,"textXHeight":0,"shapePath":{"lineWidth":1,"flatness":0.59999999999999998,"lineCapStyle":0,"elements":[{"type":"MoveToPoint","points":[[1284.9124145507826,295.4335846304898]]},{"type":"AddLine","points":[[1.59735107421875,295.43358463048963]]},{"type":"AddLine","points":[[1.59735107421875,1.8948273062705425]]},{"type":"AddLine","points":[[1284.9124145507826,1.8948273062707131]]},{"type":"CloseSubpath"},{"type":"MoveToPoint","points":[[1284.9124145507826,295.4335846304898]]}],"windingRule":0,"lineJoinStyle":0,"miterLimit":10},"isBackgroundTexture":true,"textBaseline":0,"isVerticalText":false,"textureType":5},"initialState":{"affineTransform":[-1,0,0,-1,0,0],"masksToBounds":false,"rotation":3.1415926535897931,"scale":1,"position":{"pointX":641.65753173828284,"pointY":146.76937866210966},"width":1286,"sublayerTransform":[1,0,0,0,0,1,0,0,0,0,1,0,0,0,0,1],"contentsRect":{"y":0,"x":0,"width":1,"height":1},"opacity":1,"edgeAntialiasingMask":0,"height":297,"hidden":false,"anchorPoint":{"pointX":0.50019819814346811,"pointY":0.50055288204841752}},"texture":"8A911023D4EDFC96539956C0779A9E6F"}]},{"animations":[],"initialState":{"affineTransform":[1,0,0,1,0,0],"masksToBounds":false,"rotation":0,"scale":1,"position":{"pointX":564.6436882019043,"pointY":97.284202575683594},"width":1049.3200302124023,"sublayerTransform":[1,0,0,0,0,1,0,0,0,0,1,0,0,0,0,1],"contentsRect":{"y":0,"x":0,"width":1,"height":1},"opacity":1,"edgeAntialiasingMask":251658240,"height":100.76000690460205,"hidden":false,"anchorPoint":{"pointX":0.5,"pointY":0.5}},"layers":[{"animations":[],"layers":[],"texturedRectangle":{"singleTextureOpacity":1,"textXHeight":0.5235443037974683,"textBaseline":0.76739764515357678,"isBackgroundTexture":true,"isVerticalText":false,"textColor":[0,0,0,1],"textureType":6},"initialState":{"affineTransform":[1,0,0,1,0,0],"masksToBounds":false,"rotation":0,"scale":1,"position":{"pointX":524.66000000000008,"pointY":50.3800048828125},"width":1044,"sublayerTransform":[1,0,0,0,0,1,0,0,0,0,1,0,0,0,0,1],"contentsRect":{"y":0,"x":0,"width":1,"height":1},"opacity":1,"edgeAntialiasingMask":0,"height":79,"hidden":false,"anchorPoint":{"pointX":0.50157439951695715,"pointY":0.39600258235689961}},"texture":"5C22B10F9DC8C973BFF8E2CEBB5FD141"}]}]}}]}