{"assets":{"7AF905835D9044C116557418E5390596":{"type":"texture","index":4,"assetRequest":{"type":"slide","state":"contents","slide":"none"},"url":{"native":"assets\/BDDBBEED-89F4-4FF5-9011-29BFC9820A4F.pdf"},"width":394,"height":46},"B69C968FD89725F610B4F4F0693E236F":{"type":"texture","index":10,"assetRequest":{"type":"slide","state":"contents","slide":"none"},"url":{"native":"assets\/BDDBBEED-89F4-4FF5-9011-29BFC9820A4F.pdf"},"width":1929,"height":1407},"D6DF51B62DF9E7F0906AA9AA276EF3F0":{"type":"texture","index":8,"assetRequest":{"type":"slide","state":"contents","slide":"none"},"url":{"native":"assets\/BDDBBEED-89F4-4FF5-9011-29BFC9820A4F.pdf"},"width":221,"height":58},"04306832E147839EFB0FB8E884403447":{"type":"texture","index":6,"assetRequest":{"type":"slide","state":"contents","slide":"none"},"url":{"native":"assets\/BDDBBEED-89F4-4FF5-9011-29BFC9820A4F.pdf"},"width":357,"height":46},"71908BB94A92343AD8322C86B609D427":{"type":"texture","index":5,"assetRequest":{"type":"slide","state":"contents","slide":"none"},"url":{"native":"assets\/BDDBBEED-89F4-4FF5-9011-29BFC9820A4F.pdf"},"width":544,"height":58},"C25C25FF361FB24FC35F6B120D2F252D":{"type":"texture","index":0,"assetRequest":{"type":"slide","state":"contents","slide":"none"},"url":{"native":"assets\/BDDBBEED-89F4-4FF5-9011-29BFC9820A4F.pdf"},"width":1920,"height":1080},"ED9E0B900EC4D8503D4FE4C0A46D6A6F":{"type":"texture","index":9,"assetRequest":{"type":"slide","state":"contents","slide":"none"},"url":{"native":"assets\/BDDBBEED-89F4-4FF5-9011-29BFC9820A4F.pdf"},"width":452,"height":58},"443285507267FEA0A9969F3212DC0C1C":{"type":"texture","index":7,"assetRequest":{"type":"slide","state":"contents","slide":"none"},"url":{"native":"assets\/BDDBBEED-89F4-4FF5-9011-29BFC9820A4F.pdf"},"width":224,"height":46},"1BB150B0C3FFF07E9CCBCB40A7DDC5A9":{"type":"texture","index":3,"assetRequest":{"type":"slide","state":"contents","slide":"none"},"url":{"native":"assets\/BDDBBEED-89F4-4FF5-9011-29BFC9820A4F.pdf"},"width":1289,"height":499},"8548C3E9A3139724592B21F7591C9EC2":{"type":"texture","index":2,"assetRequest":{"type":"slide","state":"contents","slide":"none"},"url":{"native":"assets\/BDDBBEED-89F4-4FF5-9011-29BFC9820A4F.pdf"},"width":345,"height":268},"60AD4FF20132BF525304E05387B0E4F8":{"type":"texture","index":11,"assetRequest":{"type":"slide","state":"contents","slide":"none"},"url":{"native":"assets\/BDDBBEED-89F4-4FF5-9011-29BFC9820A4F.pdf"},"width":1947,"height":1105},"488DFBE2390F8ED75DBE7D78A313DDB1":{"type":"texture","index":1,"assetRequest":{"type":"slide","state":"contents","slide":"none"},"url":{"native":"assets\/BDDBBEED-89F4-4FF5-9011-29BFC9820A4F.pdf"},"width":1947,"height":1105}},"events":[{"effects":[{"beginTime":0,"baseLayer":{"animations":[],"initialState":{"affineTransform":[1,0,0,1,0,0],"masksToBounds":false,"rotation":0,"scale":1,"position":{"pointX":960,"pointY":540},"width":1920,"sublayerTransform":[1,0,0,0,0,1,0,0,0,0,1,0,0,0,0,1],"contentsRect":{"y":0,"x":0,"width":1,"height":1},"opacity":1,"edgeAntialiasingMask":251658240,"height":1080,"hidden":false,"anchorPoint":{"pointX":0.5,"pointY":0.5}},"objectID":"0","layers":[{"animations":[],"initialState":{"affineTransform":[1,0,0,1,0,0],"masksToBounds":false,"rotation":0,"scale":1,"position":{"pointX":960,"pointY":540},"width":1920,"sublayerTransform":[1,0,0,0,0,1,0,0,0,0,1,-0.00035007912466775983,0,0,0,1],"contentsRect":{"y":0,"x":0,"width":1,"height":1},"opacity":1,"edgeAntialiasingMask":251658240,"height":1080,"hidden":false,"anchorPoint":{"pointX":0.5,"pointY":0.5}},"layers":[{"animations":[{"additive":false,"timeOffset":0,"beginTime":0,"repeatCount":0,"fillMode":"both","duration":2,"autoreverses":false,"animations":[{"repeatCount":0,"removedOnCompletion":true,"from":{"scalar":0},"timingFunction":"EaseInEaseOut","additive":false,"timeOffset":0,"autoreverses":false,"property":"zPosition","fillMode":"both","duration":2,"beginTime":0,"to":{"scalar":0}}],"removedOnCompletion":false}],"initialState":{"affineTransform":[1,0,0,1,0,0],"masksToBounds":false,"rotation":0,"scale":1,"position":{"pointX":960,"pointY":540},"width":1920,"sublayerTransform":[1,0,0,0,0,1,0,0,0,0,1,0,0,0,0,1],"contentsRect":{"y":0,"x":0,"width":1,"height":1},"opacity":1,"edgeAntialiasingMask":251658240,"height":1080,"hidden":false,"anchorPoint":{"pointX":0.5,"pointY":0.5}},"layers":[{"animations":[],"layers":[],"texturedRectangle":{"isBackgroundTexture":true,"singleTextureOpacity":1,"textureType":1,"textBaseline":0,"textXHeight":0,"isVerticalText":false},"initialState":{"affineTransform":[1,0,0,1,0,0],"masksToBounds":false,"rotation":0,"scale":1,"position":{"pointX":960,"pointY":540},"width":1920,"sublayerTransform":[1,0,0,0,0,1,0,0,0,0,1,0,0,0,0,1],"contentsRect":{"y":0,"x":0,"width":1,"height":1},"opacity":1,"edgeAntialiasingMask":0,"height":1080,"hidden":false,"anchorPoint":{"pointX":0.5,"pointY":0.5}},"texture":"C25C25FF361FB24FC35F6B120D2F252D"}]}]},{"animations":[{"additive":false,"timeOffset":0,"beginTime":0,"repeatCount":0,"fillMode":"both","duration":2,"autoreverses":false,"animations":[{"repeatCount":0,"removedOnCompletion":true,"from":{"scalar":0.001},"timingFunction":"EaseInEaseOut","additive":false,"timeOffset":0,"autoreverses":false,"property":"zPosition","fillMode":"both","duration":2,"beginTime":0,"to":{"scalar":0.001}}],"removedOnCompletion":false}],"initialState":{"affineTransform":[1,0,0,1,0,0],"masksToBounds":false,"rotation":0,"scale":1,"position":{"pointX":962.38039016723633,"pointY":546.64207458496094},"width":1944.195556640625,"sublayerTransform":[1,0,0,0,0,1,0,0,0,0,1,0,0,0,0,1],"contentsRect":{"y":0,"x":0,"width":1,"height":1},"opacity":1,"edgeAntialiasingMask":251658240,"height":1102.0633544921875,"hidden":false,"anchorPoint":{"pointX":0.5,"pointY":0.5}},"layers":[{"animations":[{"additive":false,"timeOffset":0,"beginTime":0,"repeatCount":0,"fillMode":"both","duration":2,"autoreverses":false,"animations":[{"repeatCount":0,"removedOnCompletion":true,"from":{"texture":"488DFBE2390F8ED75DBE7D78A313DDB1"},"timingFunction":"EaseInEaseOut","additive":false,"timeOffset":0,"autoreverses":false,"property":"contents","fillMode":"both","duration":2,"beginTime":0,"to":{"texture":"60AD4FF20132BF525304E05387B0E4F8"}}],"removedOnCompletion":false}],"layers":[],"texturedRectangle":{"singleTextureOpacity":1,"textXHeight":0,"shapePath":{"lineWidth":1,"flatness":0.59999999999999998,"lineCapStyle":0,"elements":[{"type":"MoveToPoint","points":[[1.2826118469238139,1.6103973388671875]]},{"type":"AddLine","points":[[1945.4781684875488,1.6103973388671875]]},{"type":"AddLine","points":[[1945.4781684875488,1103.6737518310547]]},{"type":"AddLine","points":[[1.2826118469238139,1103.6737518310547]]},{"type":"CloseSubpath"},{"type":"MoveToPoint","points":[[1.2826118469238139,1.6103973388671875]]}],"windingRule":0,"lineJoinStyle":0,"miterLimit":10},"isBackgroundTexture":true,"textBaseline":0,"isVerticalText":false,"textureType":5},"initialState":{"affineTransform":[1,0,0,1,0,0],"masksToBounds":false,"rotation":0,"scale":1,"position":{"pointX":972.0977783203125,"pointY":551.03167724609375},"width":1947,"sublayerTransform":[1,0,0,0,0,1,0,0,0,0,1,0,0,0,0,1],"contentsRect":{"y":0,"x":0,"width":1,"height":1},"opacity":1,"edgeAntialiasingMask":0,"height":1105,"hidden":false,"anchorPoint":{"pointX":0.49993856711208851,"pointY":0.50012857428503255}},"texture":"488DFBE2390F8ED75DBE7D78A313DDB1"}]},{"animations":[{"additive":false,"timeOffset":0,"beginTime":0,"repeatCount":0,"fillMode":"both","duration":2,"autoreverses":false,"animations":[{"repeatCount":0,"removedOnCompletion":true,"from":{"scalar":0.002},"timingFunction":"EaseInEaseOut","additive":false,"timeOffset":0,"autoreverses":false,"property":"zPosition","fillMode":"both","duration":2,"beginTime":0,"to":{"scalar":0.002}}],"removedOnCompletion":false}],"initialState":{"affineTransform":[1,0,0,1,0,0],"masksToBounds":false,"rotation":0,"scale":1,"position":{"pointX":1746.0856819152832,"pointY":938.01806640625},"width":342.0625,"sublayerTransform":[1,0,0,0,0,1,0,0,0,0,1,0,0,0,0,1],"contentsRect":{"y":0,"x":0,"width":1,"height":1},"opacity":1,"edgeAntialiasingMask":251658240,"height":264.59375,"hidden":false,"anchorPoint":{"pointX":0.5,"pointY":0.5}},"layers":[{"animations":[{"additive":false,"timeOffset":0,"beginTime":0,"repeatCount":0,"fillMode":"both","duration":2,"autoreverses":false,"animations":[{"repeatCount":0,"removedOnCompletion":true,"from":{"scalar":1},"timingFunction":"EaseInEaseOut","additive":false,"timeOffset":0,"autoreverses":false,"property":"opacity","fillMode":"forwards","duration":0.66659999999999997,"beginTime":0,"to":{"scalar":0}},{"additive":false,"timeOffset":0,"beginTime":0.66659999999999997,"from":{"scalar":true},"repeatCount":0,"fillMode":"forwards","duration":1.3334000000000001,"autoreverses":false,"property":"hidden","to":{"scalar":true},"removedOnCompletion":true}],"removedOnCompletion":false}],"layers":[],"texturedRectangle":{"isBackgroundTexture":true,"singleTextureOpacity":1,"textureType":5,"textBaseline":0,"textXHeight":0,"isVerticalText":false},"initialState":{"affineTransform":[1,0,0,1,0,0],"masksToBounds":false,"rotation":0,"scale":1,"position":{"pointX":171.02890534835205,"pointY":132.29243069887161},"width":345,"sublayerTransform":[1,0,0,0,0,1,0,0,0,0,1,0,0,0,0,1],"contentsRect":{"y":0,"x":0,"width":1,"height":1},"opacity":1,"edgeAntialiasingMask":0,"height":268,"hidden":false,"anchorPoint":{"pointX":0.49879228192358044,"pointY":0.50005082875045381}},"texture":"8548C3E9A3139724592B21F7591C9EC2"}]},{"animations":[{"additive":false,"timeOffset":0,"beginTime":0,"repeatCount":0,"fillMode":"both","duration":2,"autoreverses":false,"animations":[{"repeatCount":0,"removedOnCompletion":true,"from":{"scalar":0.0030000000000000001},"timingFunction":"EaseInEaseOut","additive":false,"timeOffset":0,"autoreverses":false,"property":"zPosition","fillMode":"both","duration":2,"beginTime":0,"to":{"scalar":0.0030000000000000001}}],"removedOnCompletion":false}],"initialState":{"affineTransform":[1,0,0,1,0,0],"masksToBounds":false,"rotation":0,"scale":1,"position":{"pointX":1238.2135009765625,"pointY":546.64208984375},"width":1286.402587890625,"sublayerTransform":[1,0,0,0,0,1,0,0,0,0,1,0,0,0,0,1],"contentsRect":{"y":0,"x":0,"width":1,"height":1},"opacity":1,"edgeAntialiasingMask":251658240,"height":496.1014404296875,"hidden":false,"anchorPoint":{"pointX":0.5,"pointY":0.5}},"layers":[{"animations":[{"additive":false,"timeOffset":0,"beginTime":0,"repeatCount":0,"fillMode":"both","duration":2,"autoreverses":false,"animations":[{"repeatCount":0,"removedOnCompletion":true,"from":{"scalar":1},"timingFunction":"EaseInEaseOut","additive":false,"timeOffset":0,"autoreverses":false,"property":"opacity","fillMode":"forwards","duration":0.66659999999999997,"beginTime":0,"to":{"scalar":0}},{"additive":false,"timeOffset":0,"beginTime":0.66659999999999997,"from":{"scalar":true},"repeatCount":0,"fillMode":"forwards","duration":1.3334000000000001,"autoreverses":false,"property":"hidden","to":{"scalar":true},"removedOnCompletion":true}],"removedOnCompletion":false}],"layers":[],"texturedRectangle":{"isBackgroundTexture":true,"singleTextureOpacity":1,"textureType":5,"textBaseline":0,"textXHeight":0,"isVerticalText":false},"initialState":{"affineTransform":[1,0,0,1,0,0],"masksToBounds":false,"rotation":0,"scale":1,"position":{"pointX":643.2012939453125,"pointY":248.05072021484375},"width":1289,"sublayerTransform":[1,0,0,0,0,1,0,0,0,0,1,0,0,0,0,1],"contentsRect":{"y":0,"x":0,"width":1,"height":1},"opacity":1,"edgeAntialiasingMask":0,"height":499,"hidden":false,"anchorPoint":{"pointX":0.49977773543565751,"pointY":0.50028474918587174}},"texture":"1BB150B0C3FFF07E9CCBCB40A7DDC5A9"}]},{"animations":[{"additive":false,"timeOffset":0,"beginTime":0,"repeatCount":0,"fillMode":"both","duration":2,"autoreverses":false,"animations":[{"repeatCount":0,"removedOnCompletion":true,"from":{"scalar":0.0040000000000000001},"timingFunction":"EaseInEaseOut","additive":false,"timeOffset":0,"autoreverses":false,"property":"zPosition","fillMode":"both","duration":2,"beginTime":0,"to":{"scalar":0.0040000000000000001}}],"removedOnCompletion":false}],"initialState":{"affineTransform":[1,0,0,1,0,0],"masksToBounds":false,"rotation":0,"scale":1,"position":{"pointX":235.18449401855469,"pointY":210.89523315429688},"width":403.56054306030273,"sublayerTransform":[1,0,0,0,0,1,0,0,0,0,1,0,0,0,0,1],"contentsRect":{"y":0,"x":0,"width":1,"height":1},"opacity":1,"edgeAntialiasingMask":251658240,"height":74.522948265075684,"hidden":false,"anchorPoint":{"pointX":0.5,"pointY":0.5}},"layers":[{"animations":[{"additive":false,"timeOffset":0,"beginTime":0,"repeatCount":0,"fillMode":"both","duration":2,"autoreverses":false,"animations":[{"repeatCount":0,"removedOnCompletion":true,"from":{"scalar":1},"timingFunction":"EaseInEaseOut","additive":false,"timeOffset":0,"autoreverses":false,"property":"opacity","fillMode":"forwards","duration":0.66659999999999997,"beginTime":0,"to":{"scalar":0}},{"additive":false,"timeOffset":0,"beginTime":0.66659999999999997,"from":{"scalar":true},"repeatCount":0,"fillMode":"forwards","duration":1.3334000000000001,"autoreverses":false,"property":"hidden","to":{"scalar":true},"removedOnCompletion":true}],"removedOnCompletion":false}],"layers":[],"texturedRectangle":{"singleTextureOpacity":1,"textXHeight":0.60483186141304346,"textBaseline":0.94712697941323987,"isBackgroundTexture":true,"isVerticalText":false,"textColor":[3.4193280384897662e-07,0.4624592661857605,0.72913676500320435,1],"textureType":6},"initialState":{"affineTransform":[1,0,0,1,0,0],"masksToBounds":false,"rotation":0,"scale":1,"position":{"pointX":201.7802734375,"pointY":37.261474609375},"width":394,"sublayerTransform":[1,0,0,0,0,1,0,0,0,0,1,0,0,0,0,1],"contentsRect":{"y":0,"x":0,"width":1,"height":1},"opacity":1,"edgeAntialiasingMask":0,"height":46,"hidden":false,"anchorPoint":{"pointX":0.50046826377132825,"pointY":0.51946160067682678}},"texture":"7AF905835D9044C116557418E5390596"}]},{"animations":[{"additive":false,"timeOffset":0,"beginTime":0,"repeatCount":0,"fillMode":"both","duration":2,"autoreverses":false,"animations":[{"repeatCount":0,"removedOnCompletion":true,"from":{"scalar":0.0050000000000000001},"timingFunction":"EaseInEaseOut","additive":false,"timeOffset":0,"autoreverses":false,"property":"zPosition","fillMode":"both","duration":2,"beginTime":0,"to":{"scalar":0.0050000000000000001}}],"removedOnCompletion":false}],"initialState":{"affineTransform":[1,0,0,1,0,0],"masksToBounds":false,"rotation":0,"scale":1,"position":{"pointX":319.21237182617188,"pointY":351.7828369140625},"width":555.5356502532959,"sublayerTransform":[1,0,0,0,0,1,0,0,0,0,1,0,0,0,0,1],"contentsRect":{"y":0,"x":0,"width":1,"height":1},"opacity":1,"edgeAntialiasingMask":251658240,"height":74.522948265075684,"hidden":false,"anchorPoint":{"pointX":0.5,"pointY":0.5}},"layers":[{"animations":[{"additive":false,"timeOffset":0,"beginTime":0,"repeatCount":0,"fillMode":"both","duration":2,"autoreverses":false,"animations":[{"repeatCount":0,"removedOnCompletion":true,"from":{"scalar":1},"timingFunction":"EaseInEaseOut","additive":false,"timeOffset":0,"autoreverses":false,"property":"opacity","fillMode":"forwards","duration":0.66659999999999997,"beginTime":0,"to":{"scalar":0}},{"additive":false,"timeOffset":0,"beginTime":0.66659999999999997,"from":{"scalar":true},"repeatCount":0,"fillMode":"forwards","duration":1.3334000000000001,"autoreverses":false,"property":"hidden","to":{"scalar":true},"removedOnCompletion":true}],"removedOnCompletion":false}],"layers":[],"texturedRectangle":{"singleTextureOpacity":1,"textXHeight":0.47969423491379309,"textBaseline":0.74923180711680448,"isBackgroundTexture":true,"isVerticalText":false,"textColor":[0.9321255087852478,0.13482958078384399,0.0465550497174263,1],"textureType":6},"initialState":{"affineTransform":[1,0,0,1,0,0],"masksToBounds":false,"rotation":0,"scale":1,"position":{"pointX":277.767822265625,"pointY":37.261474609375},"width":544,"sublayerTransform":[1,0,0,0,0,1,0,0,0,0,1,0,0,0,0,1],"contentsRect":{"y":0,"x":0,"width":1,"height":1},"opacity":1,"edgeAntialiasingMask":0,"height":58,"hidden":false,"anchorPoint":{"pointX":0.50222861942122965,"pointY":0.41004892053275271}},"texture":"71908BB94A92343AD8322C86B609D427"}]},{"animations":[{"additive":false,"timeOffset":0,"beginTime":0,"repeatCount":0,"fillMode":"both","duration":2,"autoreverses":false,"animations":[{"repeatCount":0,"removedOnCompletion":true,"from":{"scalar":0.0060000000000000001},"timingFunction":"EaseInEaseOut","additive":false,"timeOffset":0,"autoreverses":false,"property":"zPosition","fillMode":"both","duration":2,"beginTime":0,"to":{"scalar":0.0060000000000000001}}],"removedOnCompletion":false}],"initialState":{"affineTransform":[1,0,0,1,0,0],"masksToBounds":false,"rotation":0,"scale":1,"position":{"pointX":235.18449354171753,"pointY":547.70477294921875},"width":381.48534297943115,"sublayerTransform":[1,0,0,0,0,1,0,0,0,0,1,0,0,0,0,1],"contentsRect":{"y":0,"x":0,"width":1,"height":1},"opacity":1,"edgeAntialiasingMask":251658240,"height":142.5229549407959,"hidden":false,"anchorPoint":{"pointX":0.5,"pointY":0.5}},"layers":[{"animations":[{"additive":false,"timeOffset":0,"beginTime":0,"repeatCount":0,"fillMode":"both","duration":2,"autoreverses":false,"animations":[{"repeatCount":0,"removedOnCompletion":true,"from":{"scalar":1},"timingFunction":"EaseInEaseOut","additive":false,"timeOffset":0,"autoreverses":false,"property":"opacity","fillMode":"forwards","duration":0.66659999999999997,"beginTime":0,"to":{"scalar":0}},{"additive":false,"timeOffset":0,"beginTime":0.66659999999999997,"from":{"scalar":true},"repeatCount":0,"fillMode":"forwards","duration":1.3334000000000001,"autoreverses":false,"property":"hidden","to":{"scalar":true},"removedOnCompletion":true}],"removedOnCompletion":false}],"layers":[],"texturedRectangle":{"singleTextureOpacity":1,"textXHeight":0.60483186141304346,"textBaseline":0.94298646761023475,"isBackgroundTexture":true,"isVerticalText":false,"textColor":[0.0050649591721594334,0.44276615977287292,0.0017366778338328004,1],"textureType":6},"initialState":{"affineTransform":[1,0,0,1,0,0],"masksToBounds":false,"rotation":0,"scale":1,"position":{"pointX":190.74267578125,"pointY":71.261474609375},"width":357,"sublayerTransform":[1,0,0,0,0,1,0,0,0,0,1,0,0,0,0,1],"contentsRect":{"y":0,"x":0,"width":1,"height":1},"opacity":1,"edgeAntialiasingMask":0,"height":46,"hidden":false,"anchorPoint":{"pointX":0.5187240835665321,"pointY":1.2544515236564304}},"texture":"04306832E147839EFB0FB8E884403447"}]},{"animations":[{"additive":false,"timeOffset":0,"beginTime":0,"repeatCount":0,"fillMode":"both","duration":2,"autoreverses":false,"animations":[{"repeatCount":0,"removedOnCompletion":true,"from":{"scalar":0.0070000000000000001},"timingFunction":"EaseInEaseOut","additive":false,"timeOffset":0,"autoreverses":false,"property":"zPosition","fillMode":"both","duration":2,"beginTime":0,"to":{"scalar":0.0070000000000000001}}],"removedOnCompletion":false}],"initialState":{"affineTransform":[1,0,0,1,0,0],"masksToBounds":false,"rotation":0,"scale":1,"position":{"pointX":235.18449354171753,"pointY":547.70477294921875},"width":381.48534297943115,"sublayerTransform":[1,0,0,0,0,1,0,0,0,0,1,0,0,0,0,1],"contentsRect":{"y":0,"x":0,"width":1,"height":1},"opacity":1,"edgeAntialiasingMask":251658240,"height":142.5229549407959,"hidden":false,"anchorPoint":{"pointX":0.5,"pointY":0.5}},"layers":[{"animations":[{"additive":false,"timeOffset":0,"beginTime":0,"repeatCount":0,"fillMode":"both","duration":2,"autoreverses":false,"animations":[{"repeatCount":0,"removedOnCompletion":true,"from":{"scalar":1},"timingFunction":"EaseInEaseOut","additive":false,"timeOffset":0,"autoreverses":false,"property":"opacity","fillMode":"forwards","duration":0.66659999999999997,"beginTime":0,"to":{"scalar":0}},{"additive":false,"timeOffset":0,"beginTime":0.66659999999999997,"from":{"scalar":true},"repeatCount":0,"fillMode":"forwards","duration":1.3334000000000001,"autoreverses":false,"property":"hidden","to":{"scalar":true},"removedOnCompletion":true}],"removedOnCompletion":false}],"layers":[],"texturedRectangle":{"singleTextureOpacity":1,"textXHeight":0.60483186141304346,"textBaseline":0.94298646761023475,"isBackgroundTexture":true,"isVerticalText":false,"textColor":[0.0050649591721594334,0.44276615977287292,0.0017366778338328004,1],"textureType":6},"initialState":{"affineTransform":[1,0,0,1,0,0],"masksToBounds":false,"rotation":0,"scale":1,"position":{"pointX":190.74267578125,"pointY":71.261474609375},"width":224,"sublayerTransform":[1,0,0,0,0,1,0,0,0,0,1,0,0,0,0,1],"contentsRect":{"y":0,"x":0,"width":1,"height":1},"opacity":1,"edgeAntialiasingMask":0,"height":46,"hidden":false,"anchorPoint":{"pointX":0.83118079389844624,"pointY":-0.22380934590878693}},"texture":"443285507267FEA0A9969F3212DC0C1C"}]},{"animations":[{"additive":false,"timeOffset":0,"beginTime":0,"repeatCount":0,"fillMode":"both","duration":2,"autoreverses":false,"animations":[{"repeatCount":0,"removedOnCompletion":true,"from":{"scalar":0.0080000000000000002},"timingFunction":"EaseInEaseOut","additive":false,"timeOffset":0,"autoreverses":false,"property":"zPosition","fillMode":"both","duration":2,"beginTime":0,"to":{"scalar":0.0080000000000000002}}],"removedOnCompletion":false}],"initialState":{"affineTransform":[1,0,0,1,0,0],"masksToBounds":false,"rotation":0,"scale":1,"position":{"pointX":160.81086730957031,"pointY":869.10479736328125},"width":230.90674877166748,"sublayerTransform":[1,0,0,0,0,1,0,0,0,0,1,0,0,0,0,1],"contentsRect":{"y":0,"x":0,"width":1,"height":1},"opacity":1,"edgeAntialiasingMask":251658240,"height":74.522948265075684,"hidden":false,"anchorPoint":{"pointX":0.5,"pointY":0.5}},"layers":[{"animations":[{"additive":false,"timeOffset":0,"beginTime":0,"repeatCount":0,"fillMode":"both","duration":2,"autoreverses":false,"animations":[{"repeatCount":0,"removedOnCompletion":true,"from":{"scalar":1},"timingFunction":"EaseInEaseOut","additive":false,"timeOffset":0,"autoreverses":false,"property":"opacity","fillMode":"forwards","duration":0.66659999999999997,"beginTime":0,"to":{"scalar":0}},{"additive":false,"timeOffset":0,"beginTime":0.66659999999999997,"from":{"scalar":true},"repeatCount":0,"fillMode":"forwards","duration":1.3334000000000001,"autoreverses":false,"property":"hidden","to":{"scalar":true},"removedOnCompletion":true}],"removedOnCompletion":false}],"layers":[],"texturedRectangle":{"singleTextureOpacity":1,"textXHeight":0.47969423491379309,"textBaseline":0.75478284934471396,"isBackgroundTexture":true,"isVerticalText":false,"textColor":[0.82941263914108276,0.096037738025188446,0.46442997455596924,1],"textureType":6},"initialState":{"affineTransform":[1,0,0,1,0,0],"masksToBounds":false,"rotation":0,"scale":1,"position":{"pointX":115.453369140625,"pointY":37.261474609375},"width":221,"sublayerTransform":[1,0,0,0,0,1,0,0,0,0,1,0,0,0,0,1],"contentsRect":{"y":0,"x":0,"width":1,"height":1},"opacity":1,"edgeAntialiasingMask":0,"height":58,"hidden":false,"anchorPoint":{"pointX":0.50140661567584421,"pointY":0.41559996276066219}},"texture":"D6DF51B62DF9E7F0906AA9AA276EF3F0"}]},{"animations":[{"additive":false,"timeOffset":0,"beginTime":0,"repeatCount":0,"fillMode":"both","duration":2,"autoreverses":false,"animations":[{"repeatCount":0,"removedOnCompletion":true,"from":{"scalar":0.0090000000000000011},"timingFunction":"EaseInEaseOut","additive":false,"timeOffset":0,"autoreverses":false,"property":"zPosition","fillMode":"both","duration":2,"beginTime":0,"to":{"scalar":0.0090000000000000011}}],"removedOnCompletion":false}],"initialState":{"affineTransform":[1,0,0,1,0,0],"masksToBounds":false,"rotation":0,"scale":1,"position":{"pointX":275.62255859375,"pointY":743.626708984375},"width":461.64894104003906,"sublayerTransform":[1,0,0,0,0,1,0,0,0,0,1,0,0,0,0,1],"contentsRect":{"y":0,"x":0,"width":1,"height":1},"opacity":1,"edgeAntialiasingMask":251658240,"height":74.522948265075684,"hidden":false,"anchorPoint":{"pointX":0.5,"pointY":0.5}},"layers":[{"animations":[{"additive":false,"timeOffset":0,"beginTime":0,"repeatCount":0,"fillMode":"both","duration":2,"autoreverses":false,"animations":[{"repeatCount":0,"removedOnCompletion":true,"from":{"scalar":1},"timingFunction":"EaseInEaseOut","additive":false,"timeOffset":0,"autoreverses":false,"property":"opacity","fillMode":"forwards","duration":0.66659999999999997,"beginTime":0,"to":{"scalar":0}},{"additive":false,"timeOffset":0,"beginTime":0.66659999999999997,"from":{"scalar":true},"repeatCount":0,"fillMode":"forwards","duration":1.3334000000000001,"autoreverses":false,"property":"hidden","to":{"scalar":true},"removedOnCompletion":true}],"removedOnCompletion":false}],"layers":[],"texturedRectangle":{"singleTextureOpacity":1,"textXHeight":0.47969423491379309,"textBaseline":0.74653994626012343,"isBackgroundTexture":true,"isVerticalText":false,"textColor":[0.99497848749160767,0.68061012029647827,0,1],"textureType":6},"initialState":{"affineTransform":[1,0,0,1,0,0],"masksToBounds":false,"rotation":0,"scale":1,"position":{"pointX":230.824462890625,"pointY":37.261474609375},"width":452,"sublayerTransform":[1,0,0,0,0,1,0,0,0,0,1,0,0,0,0,1],"contentsRect":{"y":0,"x":0,"width":1,"height":1},"opacity":1,"edgeAntialiasingMask":0,"height":58,"hidden":false,"anchorPoint":{"pointX":0.50137732514237932,"pointY":0.40735705967607172}},"texture":"ED9E0B900EC4D8503D4FE4C0A46D6A6F"}]},{"animations":[{"additive":false,"timeOffset":0,"beginTime":0,"repeatCount":0,"fillMode":"both","duration":2,"autoreverses":false,"animations":[{"repeatCount":0,"removedOnCompletion":true,"from":{"scalar":0.01},"timingFunction":"EaseInEaseOut","additive":false,"timeOffset":0,"autoreverses":false,"property":"zPosition","fillMode":"both","duration":2,"beginTime":0,"to":{"scalar":0.01}}],"removedOnCompletion":false}],"initialState":{"affineTransform":[1,0,0,1,0,0],"masksToBounds":false,"rotation":0,"scale":1,"position":{"pointX":962.38039156794548,"pointY":695.73193311691284},"width":1925.7598876953125,"sublayerTransform":[1,0,0,0,0,1,0,0,0,0,1,0,0,0,0,1],"contentsRect":{"y":0,"x":0,"width":1,"height":1},"opacity":1,"edgeAntialiasingMask":251658240,"height":1404.199951171875,"hidden":false,"anchorPoint":{"pointX":0.5,"pointY":0.5}},"layers":[{"animations":[{"additive":false,"timeOffset":0,"beginTime":0,"repeatCount":0,"fillMode":"both","duration":2,"autoreverses":false,"animations":[{"repeatCount":0,"removedOnCompletion":true,"from":{"scalar":0},"timingFunction":"EaseInEaseOut","additive":false,"timeOffset":0,"autoreverses":false,"property":"opacity","fillMode":"both","duration":0.66659999999999997,"beginTime":1.3334000000000001,"to":{"scalar":1}},{"additive":false,"timeOffset":0,"beginTime":1.3334000000000001,"from":{"scalar":false},"repeatCount":0,"fillMode":"forwards","duration":0.66659999999999986,"autoreverses":false,"property":"hidden","to":{"scalar":false},"removedOnCompletion":true}],"removedOnCompletion":false}],"layers":[],"texturedRectangle":{"isBackgroundTexture":true,"singleTextureOpacity":1,"textureType":5,"textBaseline":0,"textXHeight":0,"isVerticalText":false},"initialState":{"affineTransform":[1,0,0,1,0,0],"masksToBounds":false,"rotation":0,"scale":1,"position":{"pointX":962.87994384765625,"pointY":702.0999755859375},"width":1929,"sublayerTransform":[1,0,0,0,0,1,0,0,0,0,1,0,0,0,0,1],"contentsRect":{"y":0,"x":0,"width":1,"height":1},"opacity":1,"edgeAntialiasingMask":0,"height":1407,"hidden":true,"anchorPoint":{"pointX":0.49993799459198834,"pointY":0.50016484230057767}},"texture":"B69C968FD89725F610B4F4F0693E236F"}]}]},"effects":[],"duration":2,"type":"transition","attributes":{"direction":0},"name":"apple:magic-move-implied-motion-path","objectID":"0"}],"automaticPlay":false,"hyperlinks":[],"accessibility":[{"text":"Street Hierarchy","targetRectangle":{"y":710.36523485183716,"x":49.298088073730469,"width":452.64892578125,"height":66.52294921875}},{"text":"4,000 - 5,000 People","targetRectangle":{"y":318.52136278152466,"x":45.944546699523926,"width":546.53564453125,"height":66.52294921875}},{"text":"Self Contained","targetRectangle":{"y":177.63375902175903,"x":37.90422248840332,"width":394.560546875,"height":66.52294921875}},{"text":"Stability","targetRectangle":{"y":835.84332323074341,"x":49.857492923736572,"width":221.90673828125,"height":66.52294921875}},{"text":"cc_comp-1950-inset.png","targetRectangle":{"y":298.59136962890625,"x":595.01220703125,"width":1286.402587890625,"height":496.1014404296875}},{"text":"cc_comp-1950.png","targetRectangle":{"y":805.72119140625,"x":1575.0544319152832,"width":342.0625,"height":264.59375}},{"text":"Institutions + ","targetRectangle":{"y":480.4432954788208,"x":48.441822052001953,"width":372.4853515625,"height":66.52294921875}},{"text":"Services","targetRectangle":{"y":548.4432954788208,"x":48.441822052001953,"width":225.263671875,"height":66.52294921875}}],"baseLayer":{"animations":[],"initialState":{"affineTransform":[1,0,0,1,0,0],"masksToBounds":false,"rotation":0,"scale":1,"position":{"pointX":960,"pointY":540},"width":1920,"sublayerTransform":[1,0,0,0,0,1,0,0,0,0,1,0,0,0,0,1],"contentsRect":{"y":0,"x":0,"width":1,"height":1},"opacity":1,"edgeAntialiasingMask":251658240,"height":1080,"hidden":false,"anchorPoint":{"pointX":0.5,"pointY":0.5}},"objectID":"0","layers":[{"animations":[],"initialState":{"affineTransform":[1,0,0,1,0,0],"masksToBounds":false,"rotation":0,"scale":1,"position":{"pointX":960,"pointY":540},"width":1920,"sublayerTransform":[1,0,0,0,0,1,0,0,0,0,1,-0.00035007912466775983,0,0,0,1],"contentsRect":{"y":0,"x":0,"width":1,"height":1},"opacity":1,"edgeAntialiasingMask":251658240,"height":1080,"hidden":false,"anchorPoint":{"pointX":0.5,"pointY":0.5}},"layers":[{"animations":[],"initialState":{"affineTransform":[1,0,0,1,0,0],"masksToBounds":false,"rotation":0,"scale":1,"position":{"pointX":960,"pointY":540},"width":1920,"sublayerTransform":[1,0,0,0,0,1,0,0,0,0,1,0,0,0,0,1],"contentsRect":{"y":0,"x":0,"width":1,"height":1},"opacity":1,"edgeAntialiasingMask":251658240,"height":1080,"hidden":false,"anchorPoint":{"pointX":0.5,"pointY":0.5}},"layers":[{"animations":[],"layers":[],"texturedRectangle":{"isBackgroundTexture":true,"singleTextureOpacity":1,"textureType":1,"textBaseline":0,"textXHeight":0,"isVerticalText":false},"initialState":{"affineTransform":[1,0,0,1,0,0],"masksToBounds":false,"rotation":0,"scale":1,"position":{"pointX":960,"pointY":540},"width":1920,"sublayerTransform":[1,0,0,0,0,1,0,0,0,0,1,0,0,0,0,1],"contentsRect":{"y":0,"x":0,"width":1,"height":1},"opacity":1,"edgeAntialiasingMask":0,"height":1080,"hidden":false,"anchorPoint":{"pointX":0.5,"pointY":0.5}},"texture":"C25C25FF361FB24FC35F6B120D2F252D"}]}]},{"animations":[],"initialState":{"affineTransform":[1,0,0,1,0,0],"masksToBounds":false,"rotation":0,"scale":1,"position":{"pointX":962.38039016723633,"pointY":546.64207458496094},"width":1944.195556640625,"sublayerTransform":[1,0,0,0,0,1,0,0,0,0,1,0,0,0,0,1],"contentsRect":{"y":0,"x":0,"width":1,"height":1},"opacity":1,"edgeAntialiasingMask":251658240,"height":1102.0633544921875,"hidden":false,"anchorPoint":{"pointX":0.5,"pointY":0.5}},"layers":[{"animations":[],"layers":[],"texturedRectangle":{"singleTextureOpacity":1,"textXHeight":0,"shapePath":{"lineWidth":1,"flatness":0.59999999999999998,"lineCapStyle":0,"elements":[{"type":"MoveToPoint","points":[[1.2826118469238139,1.6103973388671875]]},{"type":"AddLine","points":[[1945.4781684875488,1.6103973388671875]]},{"type":"AddLine","points":[[1945.4781684875488,1103.6737518310547]]},{"type":"AddLine","points":[[1.2826118469238139,1103.6737518310547]]},{"type":"CloseSubpath"},{"type":"MoveToPoint","points":[[1.2826118469238139,1.6103973388671875]]}],"windingRule":0,"lineJoinStyle":0,"miterLimit":10},"isBackgroundTexture":true,"textBaseline":0,"isVerticalText":false,"textureType":5},"initialState":{"affineTransform":[1,0,0,1,0,0],"masksToBounds":false,"rotation":0,"scale":1,"position":{"pointX":972.0977783203125,"pointY":551.03167724609375},"width":1947,"sublayerTransform":[1,0,0,0,0,1,0,0,0,0,1,0,0,0,0,1],"contentsRect":{"y":0,"x":0,"width":1,"height":1},"opacity":1,"edgeAntialiasingMask":0,"height":1105,"hidden":false,"anchorPoint":{"pointX":0.49993856711208851,"pointY":0.50012857428503255}},"texture":"488DFBE2390F8ED75DBE7D78A313DDB1"}]},{"animations":[],"initialState":{"affineTransform":[1,0,0,1,0,0],"masksToBounds":false,"rotation":0,"scale":1,"position":{"pointX":1746.0856819152832,"pointY":938.01806640625},"width":342.0625,"sublayerTransform":[1,0,0,0,0,1,0,0,0,0,1,0,0,0,0,1],"contentsRect":{"y":0,"x":0,"width":1,"height":1},"opacity":1,"edgeAntialiasingMask":251658240,"height":264.59375,"hidden":false,"anchorPoint":{"pointX":0.5,"pointY":0.5}},"layers":[{"animations":[],"layers":[],"texturedRectangle":{"isBackgroundTexture":true,"singleTextureOpacity":1,"textureType":5,"textBaseline":0,"textXHeight":0,"isVerticalText":false},"initialState":{"affineTransform":[1,0,0,1,0,0],"masksToBounds":false,"rotation":0,"scale":1,"position":{"pointX":171.02890534835205,"pointY":132.29243069887161},"width":345,"sublayerTransform":[1,0,0,0,0,1,0,0,0,0,1,0,0,0,0,1],"contentsRect":{"y":0,"x":0,"width":1,"height":1},"opacity":1,"edgeAntialiasingMask":0,"height":268,"hidden":false,"anchorPoint":{"pointX":0.49879228192358044,"pointY":0.50005082875045381}},"texture":"8548C3E9A3139724592B21F7591C9EC2"}]},{"animations":[],"initialState":{"affineTransform":[1,0,0,1,0,0],"masksToBounds":false,"rotation":0,"scale":1,"position":{"pointX":1238.2135009765625,"pointY":546.64208984375},"width":1286.402587890625,"sublayerTransform":[1,0,0,0,0,1,0,0,0,0,1,0,0,0,0,1],"contentsRect":{"y":0,"x":0,"width":1,"height":1},"opacity":1,"edgeAntialiasingMask":251658240,"height":496.1014404296875,"hidden":false,"anchorPoint":{"pointX":0.5,"pointY":0.5}},"layers":[{"animations":[],"layers":[],"texturedRectangle":{"isBackgroundTexture":true,"singleTextureOpacity":1,"textureType":5,"textBaseline":0,"textXHeight":0,"isVerticalText":false},"initialState":{"affineTransform":[1,0,0,1,0,0],"masksToBounds":false,"rotation":0,"scale":1,"position":{"pointX":643.2012939453125,"pointY":248.05072021484375},"width":1289,"sublayerTransform":[1,0,0,0,0,1,0,0,0,0,1,0,0,0,0,1],"contentsRect":{"y":0,"x":0,"width":1,"height":1},"opacity":1,"edgeAntialiasingMask":0,"height":499,"hidden":false,"anchorPoint":{"pointX":0.49977773543565751,"pointY":0.50028474918587174}},"texture":"1BB150B0C3FFF07E9CCBCB40A7DDC5A9"}]},{"animations":[],"initialState":{"affineTransform":[1,0,0,1,0,0],"masksToBounds":false,"rotation":0,"scale":1,"position":{"pointX":235.18449401855469,"pointY":210.89523315429688},"width":403.56054306030273,"sublayerTransform":[1,0,0,0,0,1,0,0,0,0,1,0,0,0,0,1],"contentsRect":{"y":0,"x":0,"width":1,"height":1},"opacity":1,"edgeAntialiasingMask":251658240,"height":74.522948265075684,"hidden":false,"anchorPoint":{"pointX":0.5,"pointY":0.5}},"layers":[{"animations":[],"layers":[],"texturedRectangle":{"singleTextureOpacity":1,"textXHeight":0.60483186141304346,"textBaseline":0.94712697941323987,"isBackgroundTexture":true,"isVerticalText":false,"textColor":[3.4193280384897662e-07,0.4624592661857605,0.72913676500320435,1],"textureType":6},"initialState":{"affineTransform":[1,0,0,1,0,0],"masksToBounds":false,"rotation":0,"scale":1,"position":{"pointX":201.7802734375,"pointY":37.261474609375},"width":394,"sublayerTransform":[1,0,0,0,0,1,0,0,0,0,1,0,0,0,0,1],"contentsRect":{"y":0,"x":0,"width":1,"height":1},"opacity":1,"edgeAntialiasingMask":0,"height":46,"hidden":false,"anchorPoint":{"pointX":0.50046826377132825,"pointY":0.51946160067682678}},"texture":"7AF905835D9044C116557418E5390596"}]},{"animations":[],"initialState":{"affineTransform":[1,0,0,1,0,0],"masksToBounds":false,"rotation":0,"scale":1,"position":{"pointX":319.21237182617188,"pointY":351.7828369140625},"width":555.5356502532959,"sublayerTransform":[1,0,0,0,0,1,0,0,0,0,1,0,0,0,0,1],"contentsRect":{"y":0,"x":0,"width":1,"height":1},"opacity":1,"edgeAntialiasingMask":251658240,"height":74.522948265075684,"hidden":false,"anchorPoint":{"pointX":0.5,"pointY":0.5}},"layers":[{"animations":[],"layers":[],"texturedRectangle":{"singleTextureOpacity":1,"textXHeight":0.47969423491379309,"textBaseline":0.74923180711680448,"isBackgroundTexture":true,"isVerticalText":false,"textColor":[0.9321255087852478,0.13482958078384399,0.0465550497174263,1],"textureType":6},"initialState":{"affineTransform":[1,0,0,1,0,0],"masksToBounds":false,"rotation":0,"scale":1,"position":{"pointX":277.767822265625,"pointY":37.261474609375},"width":544,"sublayerTransform":[1,0,0,0,0,1,0,0,0,0,1,0,0,0,0,1],"contentsRect":{"y":0,"x":0,"width":1,"height":1},"opacity":1,"edgeAntialiasingMask":0,"height":58,"hidden":false,"anchorPoint":{"pointX":0.50222861942122965,"pointY":0.41004892053275271}},"texture":"71908BB94A92343AD8322C86B609D427"}]},{"animations":[],"initialState":{"affineTransform":[1,0,0,1,0,0],"masksToBounds":false,"rotation":0,"scale":1,"position":{"pointX":235.18449354171753,"pointY":547.70477294921875},"width":381.48534297943115,"sublayerTransform":[1,0,0,0,0,1,0,0,0,0,1,0,0,0,0,1],"contentsRect":{"y":0,"x":0,"width":1,"height":1},"opacity":1,"edgeAntialiasingMask":251658240,"height":142.5229549407959,"hidden":false,"anchorPoint":{"pointX":0.5,"pointY":0.5}},"layers":[{"animations":[],"layers":[],"texturedRectangle":{"singleTextureOpacity":1,"textXHeight":0.60483186141304346,"textBaseline":0.94298646761023475,"isBackgroundTexture":true,"isVerticalText":false,"textColor":[0.0050649591721594334,0.44276615977287292,0.0017366778338328004,1],"textureType":6},"initialState":{"affineTransform":[1,0,0,1,0,0],"masksToBounds":false,"rotation":0,"scale":1,"position":{"pointX":190.74267578125,"pointY":71.261474609375},"width":357,"sublayerTransform":[1,0,0,0,0,1,0,0,0,0,1,0,0,0,0,1],"contentsRect":{"y":0,"x":0,"width":1,"height":1},"opacity":1,"edgeAntialiasingMask":0,"height":46,"hidden":false,"anchorPoint":{"pointX":0.5187240835665321,"pointY":1.2544515236564304}},"texture":"04306832E147839EFB0FB8E884403447"}]},{"animations":[],"initialState":{"affineTransform":[1,0,0,1,0,0],"masksToBounds":false,"rotation":0,"scale":1,"position":{"pointX":235.18449354171753,"pointY":547.70477294921875},"width":381.48534297943115,"sublayerTransform":[1,0,0,0,0,1,0,0,0,0,1,0,0,0,0,1],"contentsRect":{"y":0,"x":0,"width":1,"height":1},"opacity":1,"edgeAntialiasingMask":251658240,"height":142.5229549407959,"hidden":false,"anchorPoint":{"pointX":0.5,"pointY":0.5}},"layers":[{"animations":[],"layers":[],"texturedRectangle":{"singleTextureOpacity":1,"textXHeight":0.60483186141304346,"textBaseline":0.94298646761023475,"isBackgroundTexture":true,"isVerticalText":false,"textColor":[0.0050649591721594334,0.44276615977287292,0.0017366778338328004,1],"textureType":6},"initialState":{"affineTransform":[1,0,0,1,0,0],"masksToBounds":false,"rotation":0,"scale":1,"position":{"pointX":190.74267578125,"pointY":71.261474609375},"width":224,"sublayerTransform":[1,0,0,0,0,1,0,0,0,0,1,0,0,0,0,1],"contentsRect":{"y":0,"x":0,"width":1,"height":1},"opacity":1,"edgeAntialiasingMask":0,"height":46,"hidden":false,"anchorPoint":{"pointX":0.83118079389844624,"pointY":-0.22380934590878693}},"texture":"443285507267FEA0A9969F3212DC0C1C"}]},{"animations":[],"initialState":{"affineTransform":[1,0,0,1,0,0],"masksToBounds":false,"rotation":0,"scale":1,"position":{"pointX":160.81086730957031,"pointY":869.10479736328125},"width":230.90674877166748,"sublayerTransform":[1,0,0,0,0,1,0,0,0,0,1,0,0,0,0,1],"contentsRect":{"y":0,"x":0,"width":1,"height":1},"opacity":1,"edgeAntialiasingMask":251658240,"height":74.522948265075684,"hidden":false,"anchorPoint":{"pointX":0.5,"pointY":0.5}},"layers":[{"animations":[],"layers":[],"texturedRectangle":{"singleTextureOpacity":1,"textXHeight":0.47969423491379309,"textBaseline":0.75478284934471396,"isBackgroundTexture":true,"isVerticalText":false,"textColor":[0.82941263914108276,0.096037738025188446,0.46442997455596924,1],"textureType":6},"initialState":{"affineTransform":[1,0,0,1,0,0],"masksToBounds":false,"rotation":0,"scale":1,"position":{"pointX":115.453369140625,"pointY":37.261474609375},"width":221,"sublayerTransform":[1,0,0,0,0,1,0,0,0,0,1,0,0,0,0,1],"contentsRect":{"y":0,"x":0,"width":1,"height":1},"opacity":1,"edgeAntialiasingMask":0,"height":58,"hidden":false,"anchorPoint":{"pointX":0.50140661567584421,"pointY":0.41559996276066219}},"texture":"D6DF51B62DF9E7F0906AA9AA276EF3F0"}]},{"animations":[],"initialState":{"affineTransform":[1,0,0,1,0,0],"masksToBounds":false,"rotation":0,"scale":1,"position":{"pointX":275.62255859375,"pointY":743.626708984375},"width":461.64894104003906,"sublayerTransform":[1,0,0,0,0,1,0,0,0,0,1,0,0,0,0,1],"contentsRect":{"y":0,"x":0,"width":1,"height":1},"opacity":1,"edgeAntialiasingMask":251658240,"height":74.522948265075684,"hidden":false,"anchorPoint":{"pointX":0.5,"pointY":0.5}},"layers":[{"animations":[],"layers":[],"texturedRectangle":{"singleTextureOpacity":1,"textXHeight":0.47969423491379309,"textBaseline":0.74653994626012343,"isBackgroundTexture":true,"isVerticalText":false,"textColor":[0.99497848749160767,0.68061012029647827,0,1],"textureType":6},"initialState":{"affineTransform":[1,0,0,1,0,0],"masksToBounds":false,"rotation":0,"scale":1,"position":{"pointX":230.824462890625,"pointY":37.261474609375},"width":452,"sublayerTransform":[1,0,0,0,0,1,0,0,0,0,1,0,0,0,0,1],"contentsRect":{"y":0,"x":0,"width":1,"height":1},"opacity":1,"edgeAntialiasingMask":0,"height":58,"hidden":false,"anchorPoint":{"pointX":0.50137732514237932,"pointY":0.40735705967607172}},"texture":"ED9E0B900EC4D8503D4FE4C0A46D6A6F"}]},{"animations":[],"initialState":{"affineTransform":[1,0,0,1,0,0],"masksToBounds":false,"rotation":0,"scale":1,"position":{"pointX":962.38039156794548,"pointY":695.73193311691284},"width":1925.7598876953125,"sublayerTransform":[1,0,0,0,0,1,0,0,0,0,1,0,0,0,0,1],"contentsRect":{"y":0,"x":0,"width":1,"height":1},"opacity":1,"edgeAntialiasingMask":251658240,"height":1404.199951171875,"hidden":false,"anchorPoint":{"pointX":0.5,"pointY":0.5}},"layers":[{"animations":[],"layers":[],"texturedRectangle":{"isBackgroundTexture":true,"singleTextureOpacity":1,"textureType":5,"textBaseline":0,"textXHeight":0,"isVerticalText":false},"initialState":{"affineTransform":[1,0,0,1,0,0],"masksToBounds":false,"rotation":0,"scale":1,"position":{"pointX":962.87994384765625,"pointY":702.0999755859375},"width":1929,"sublayerTransform":[1,0,0,0,0,1,0,0,0,0,1,0,0,0,0,1],"contentsRect":{"y":0,"x":0,"width":1,"height":1},"opacity":1,"edgeAntialiasingMask":0,"height":1407,"hidden":true,"anchorPoint":{"pointX":0.49993799459198834,"pointY":0.50016484230057767}},"texture":"B69C968FD89725F610B4F4F0693E236F"}]}]}}]}